LICENSE
MANIFEST.in
README.rst
setup.cfg
setup.py
django_kp_static_version.egg-info/PKG-INFO
django_kp_static_version.egg-info/SOURCES.txt
django_kp_static_version.egg-info/dependency_links.txt
django_kp_static_version.egg-info/top_level.txt
kp_static_version/__init__.py
kp_static_version/admin.py
kp_static_version/apps.py
kp_static_version/models.py
kp_static_version/tests.py
kp_static_version/views.py
kp_static_version/migrations/__init__.py
kp_static_version/templatetags/__init__.py
kp_static_version/templatetags/kp_static.py