Metadata-Version: 1.1
Name: django-kp-static-version
Version: 0.2
Summary: kp_static_version is a simple Django app to add a version number to static files and force browsers to use the latest version of the file.
Home-page: https://github.com/KernelPan1k/django-kp-static-version
Author: kernel-panik
Author-email: UNKNOWN
License: GPLv3
Platform: UNKNOWN
Classifier: Environment :: Web Environment
Classifier: Framework :: Django
Classifier: Intended Audience :: Developers
Classifier: License :: OSI Approved :: GNU General Public License v3 (GPLv3)
Classifier: Operating System :: OS Independent
Classifier: Programming Language :: Python
Classifier: Programming Language :: Python :: 2
Classifier: Programming Language :: Python :: 3
Classifier: Topic :: Internet :: WWW/HTTP
Classifier: Topic :: Internet :: WWW/HTTP :: Dynamic Content
